MANIFEST.in
README.rst
setup.py
dlp_polls.egg-info/PKG-INFO
dlp_polls.egg-info/SOURCES.txt
dlp_polls.egg-info/dependency_links.txt
dlp_polls.egg-info/top_level.txt
polls/__init__.py
polls/admin.py
polls/helpers.py
polls/models.py
polls/tests.py
polls/urls.py
polls/views.py
polls/static/base.css
polls/templates/base.html
polls/templates/poll_detail.html
polls/templates/poll_list.html
polls/templates/poll_result.html