Metadata-Version: 1.0
Name: dlp-polls
Version: 1.1
Summary: Polls app from DLP
Home-page: UNKNOWN
Author: laurafeier
Author-email: laurafeier@3pillarglobal.com
License: UNKNOWN
Platform: UNKNOWN
